rpakeyboard/__init__.py
rpakeyboard/keyboard.py
rpakeyboard-3.0.dist-info/LICENSE
rpakeyboard-3.0.dist-info/METADATA
rpakeyboard-3.0.dist-info/WHEEL
rpakeyboard-3.0.dist-info/top_level.txt
rpakeyboard-3.0.dist-info/RECORD
