Metadata-Version: 2.1
Name: rpakeyboard
Version: 3.0
Summary: use pywinio control windows keyboard tools
Home-page: UNKNOWN
Author: cengceng
Author-email: 643164464@qq.com
License: MIT
Platform: UNKNOWN
Requires-Dist: pytest-runner (==5.3.0)
Requires-Dist: pywinio (==0.3.1)
